communardo/__init__.py
communardo/metadata/__init__.py
communardo/metadata/client.py
communardo/metadata/models/__init__.py
communardo/metadata/models/metadatavalue.py
communardo/metadata/models/pagemetadata.py
communardo_metadata-0.4.0.dist-info/DESCRIPTION.rst
communardo_metadata-0.4.0.dist-info/METADATA
communardo_metadata-0.4.0.dist-info/RECORD
communardo_metadata-0.4.0.dist-info/WHEEL
communardo_metadata-0.4.0.dist-info/metadata.json
communardo_metadata-0.4.0.dist-info/top_level.txt
tests/models/__init__.py
tests/models/test_metadatavalue.py
tests/models/test_pagemetadata.py
